turbo/__init__.py
turbo/gp.py
turbo/turbo_1.py
turbo/turbo_m.py
turbo/utils.py
uber_turbo-0.1.3.dist-info/LICENSE.md
uber_turbo-0.1.3.dist-info/METADATA
uber_turbo-0.1.3.dist-info/WHEEL
uber_turbo-0.1.3.dist-info/RECORD
