Metadata-Version: 2.1
Name: uber-turbo
Version: 0.1.3
Summary: Packaged fork from uber-research/TuRBO
License: https://github.com/uber-research/TuRBO/blob/master/LICENSE.md
Author: Uber Reasearch
Requires-Python: >=3.11,<4.0
Classifier: License :: Other/Proprietary License
Classifier: Programming Language :: Python :: 3
Classifier: Programming Language :: Python :: 3.11
Classifier: Programming Language :: Python :: 3.12
Requires-Dist: gpytorch (>=1.11,<2.0)
Requires-Dist: numpy (>=1.26.4,<2.0.0)
Requires-Dist: torch (>=2.3.0,<3.0.0)
